talkgooder/__init__.py
talkgooder/talkgooder.py
talkgooder-1.1.5.dist-info/licenses/LICENSE.md
talkgooder-1.1.5.dist-info/METADATA
talkgooder-1.1.5.dist-info/WHEEL
talkgooder-1.1.5.dist-info/top_level.txt
talkgooder-1.1.5.dist-info/RECORD
