Metadata-Version: 2.4
Name: talkgooder
Version: 1.1.5
Summary: Smooth out grammar, punctuation, and number-related corner cases when formatting text for human consumption
Maintainer-email: Brian Warner <brian@bdwarner.com>
Project-URL: Homepage, https://brianwarner.github.io/talkgooder/
Project-URL: Documentation, https://brianwarner.github.io/talkgooder/
Project-URL: Repository, https://github.com/brianwarner/talkgooder
Project-URL: Issues, https://github.com/brianwarner/talkgooder/issues
Classifier: Development Status :: 5 - Production/Stable
Classifier: Intended Audience :: Developers
Classifier: Topic :: Text Processing :: Linguistic
Classifier: License :: OSI Approved :: MIT License
Requires-Python: >=3.10
License-File: LICENSE.md
Dynamic: license-file
